a10y/__init__.py
a10y/a10y.css
a10y/a10y.py
a10y/a10y.spec
a10y/a10y.tcss
a10y/app.py
a10y/config.toml
a10y/main.py
a10y/widgets.py
eida_a10y-1.0.6.dist-info/METADATA
eida_a10y-1.0.6.dist-info/WHEEL
eida_a10y-1.0.6.dist-info/entry_points.txt
eida_a10y-1.0.6.dist-info/licenses/LICENSE
eida_a10y-1.0.6.dist-info/RECORD
