Metadata-Version: 2.4
Name: eida-a10y
Version: 1.0.6
License-File: LICENSE
Requires-Python: <4.0,>=3.11
Requires-Dist: aiohttp>=3.11.12
Requires-Dist: aiosignal>=1.3.1
Requires-Dist: appdirs>=1.4.4
Requires-Dist: async-timeout>=4.0.3
Requires-Dist: attrs>=23.1.0
Requires-Dist: certifi>=2023.11.17
Requires-Dist: charset-normalizer>=3.3.2
Requires-Dist: click>=8.1.7
Requires-Dist: frozenlist>=1.5.0
Requires-Dist: idna>=3.4
Requires-Dist: importlib-metadata>=6.8.0
Requires-Dist: linkify-it-py>=2.0.2
Requires-Dist: markdown-it-py[linkify,plugins]>=3.0.0
Requires-Dist: mdit-py-plugins>=0.4.0
Requires-Dist: mdurl>=0.1.2
Requires-Dist: msgpack>=1.1.0
Requires-Dist: multidict>=6.0.4
Requires-Dist: pygments>=2.17.2
Requires-Dist: pytest-asyncio>=0.25.3
Requires-Dist: pytest>=8.3.4
Requires-Dist: requests>=2.31.0
Requires-Dist: rich>=13.7.0
Requires-Dist: textual-autocomplete==2.1.0b0
Requires-Dist: textual-dev>=1.2.1
Requires-Dist: textual==0.43.2
Requires-Dist: tomli>=2.0.1
Requires-Dist: typing-extensions>=4.12.0
Requires-Dist: uc-micro-py>=1.0.2
Requires-Dist: urllib3>=2.1.0
Requires-Dist: yarl>=1.17.0
Requires-Dist: zipp>=3.17.0
